<?xml version="1.0" encoding="UTF-8"?>
<objects serializationModel="Studio.02.02.00">
	<object class="ParameterPreset" id="{1482ce4e-f025-4dfa-876f-b6c3528d6547}">
		<property name="name">
			<value>groundType</value>
		</property>
		<relationship name="folder">
			<destination>{272ffa37-b707-4a22-92d5-7566d66033d5}</destination>
		</relationship>
		<relationship name="parameter">
			<destination>{2b17b04e-0735-408b-a245-ba250ec457a4}</destination>
		</relationship>
	</object>
	<object class="GameParameter" id="{2b17b04e-0735-408b-a245-ba250ec457a4}">
		<property name="parameterType">
			<value>2</value>
		</property>
		<property name="maximum">
			<value>3</value>
		</property>
		<property name="enumerationLabels">
			<value>Concrete</value>
			<value>Grass</value>
			<value>Glass</value>
		</property>
		<property name="initialValue">
			<value>0</value>
		</property>
	</object>
</objects>
