<?xml version="1.0" encoding="UTF-8"?>
<objects serializationModel="Studio.02.02.00">
	<object class="AudioFile" id="{bfd8ef9a-6780-459e-b0eb-27f8bdf0765f}">
		<property name="assetPath">
			<value>SFX/Portinha de metal/Portinha de metal abrindo_02.wav</value>
		</property>
		<property name="frequencyInKHz">
			<value>48</value>
		</property>
		<property name="channelCount">
			<value>2</value>
		</property>
		<property name="length">
			<value>0.85450000000000004</value>
		</property>
		<relationship name="masterAssetFolder">
			<destination>{f2013596-3c4b-41d8-b9a8-7612b8163dcf}</destination>
		</relationship>
	</object>
</objects>
